eyeblue/__init__.py
eyeblue/config.py
eyeblue/quotations.py
eyeblue/stream.py
eyeblue/stream2.py
eyeblue/trade.py
eyeblue-1.1.3.dist-info/DESCRIPTION.rst
eyeblue-1.1.3.dist-info/METADATA
eyeblue-1.1.3.dist-info/RECORD
eyeblue-1.1.3.dist-info/WHEEL
eyeblue-1.1.3.dist-info/metadata.json
eyeblue-1.1.3.dist-info/top_level.txt
