Metadata-Version: 2.0
Name: eyeblue
Version: 1.1.3
Summary: A utility for digital cash
Home-page: https://www.blueye.info
Author: banjuanshua
Author-email: 593474341@qq.com
License: UNKNOWN
Keywords: Digital Cash Data
Platform: UNKNOWN
